twittergraph/__init__.py
twittergraph/entities.py
twittergraph/pipelines.py
twittergraph/settings.py
twittergraph/twitter.py
twittergraph/utils.py
twittergraph-1.2.5.dist-info/DESCRIPTION.rst
twittergraph-1.2.5.dist-info/METADATA
twittergraph-1.2.5.dist-info/RECORD
twittergraph-1.2.5.dist-info/WHEEL
twittergraph-1.2.5.dist-info/entry_points.txt
twittergraph-1.2.5.dist-info/metadata.json
twittergraph-1.2.5.dist-info/top_level.txt
