Metadata-Version: 2.0
Name: twittergraph
Version: 1.2.5
Summary: TwitterGraph Extractor de datos y Generacion de grafos
Home-page: https://bitbucket.org/HugoAlvarez/twittergraph
Author: Hugo Alvarez Lucena
Author-email: hugo.alvarez@mail.escuelaing.edu.co
License: MIT
Keywords: extract generate Twitter graph
Platform: UNKNOWN
Classifier: Development Status :: 5 - Production/Stable
Classifier: Intended Audience :: Developers
Classifier: Topic :: Software Development :: Build Tools
Classifier: License :: OSI Approved :: MIT License
Classifier: Programming Language :: Python :: 2
Classifier: Programming Language :: Python :: 2.7
Classifier: Programming Language :: Python :: 3
Classifier: Programming Language :: Python :: 3.3
Classifier: Programming Language :: Python :: 3.4
Classifier: Programming Language :: Python :: 3.5
Classifier: Programming Language :: Python :: 3.6
Requires-Dist: selenium
Provides-Extra: dev
Requires-Dist: check-manifest; extra == 'dev'
Provides-Extra: test
Requires-Dist: coverage; extra == 'test'
